Metadata-Version: 2.1
Name: devtools-html-to-md
Version: 1.0.1
Summary: HTML to Markdown converter
Home-page: https://devtools.at/tools/html-to-markdown
Author: DevTools.at
Author-email: hello@devtools.at
Project-URL: Homepage, https://devtools.at/tools/html-to-markdown
Project-URL: Repository, https://github.com/devtools-at/html-to-markdown
Classifier: Development Status :: 4 - Beta
Classifier: Intended Audience :: Developers
Classifier: License :: OSI Approved :: MIT License
Classifier: Programming Language :: Python :: 3
Requires-Python: >=3.8
